alphabase/__init__.py
alphabase/utils.py
alphabase/yaml_utils.py
alphabase/constants/__init__.py
alphabase/constants/_const.py
alphabase/constants/aa.py
alphabase/constants/atom.py
alphabase/constants/element.py
alphabase/constants/isotope.py
alphabase/constants/modification.py
alphabase/constants/spectral_library.py
alphabase/constants/const_files/__emass_element.yaml
alphabase/constants/const_files/amino_acid.tsv
alphabase/constants/const_files/common_constants.yaml
alphabase/constants/const_files/contaminants.fasta
alphabase/constants/const_files/modification.tsv
alphabase/constants/const_files/nist_element.yaml
alphabase/constants/const_files/pg_reader.yaml
alphabase/constants/const_files/protease.yaml
alphabase/constants/const_files/psm_reader.yaml
alphabase/constants/const_files/quant_reader_config.yaml
alphabase/io/__init__.py
alphabase/io/hdf.py
alphabase/io/tempmmap.py
alphabase/peptide/__init__.py
alphabase/peptide/fragment.py
alphabase/peptide/mass_calc.py
alphabase/peptide/mobility.py
alphabase/peptide/precursor.py
alphabase/pg_reader/__init__.py
alphabase/pg_reader/alphadia_pg_reader.py
alphabase/pg_reader/alphapept_pg_reader.py
alphabase/pg_reader/diann_pg_reader.py
alphabase/pg_reader/directlfq_pg_reader.py
alphabase/pg_reader/fragpipe_pg_reader.py
alphabase/pg_reader/keys.py
alphabase/pg_reader/maxquant_pg_reader.py
alphabase/pg_reader/mztab_pg_reader.py
alphabase/pg_reader/pg_reader.py
alphabase/pg_reader/spectronaut_reader.py
alphabase/protein/__init__.py
alphabase/protein/fasta.py
alphabase/protein/inference.py
alphabase/protein/lcp_digest.py
alphabase/protein/protein_level_decoy.py
alphabase/psm_reader/__init__.py
alphabase/psm_reader/alphadia_reader.py
alphabase/psm_reader/alphapept_reader.py
alphabase/psm_reader/dia_psm_reader.py
alphabase/psm_reader/keys.py
alphabase/psm_reader/maxquant_reader.py
alphabase/psm_reader/modification_mapper.py
alphabase/psm_reader/msfragger_reader.py
alphabase/psm_reader/pfind_reader.py
alphabase-1.8.0.dist-info/licenses/LICENSE.txt
alphabase-1.8.0.dist-info/METADATA
alphabase-1.8.0.dist-info/WHEEL
alphabase-1.8.0.dist-info/top_level.txt
alphabase-1.8.0.dist-info/RECORD
