Metadata-Version: 2.4
Name: alphabase
Version: 1.8.0
Summary: An infrastructure Python package of the AlphaX ecosystem
Author-email: Mann Labs <jalew188@gmail.com>
License:                                  Apache License
Project-URL: Paper preprint, https://www.biochem.mpg.de/mann
Project-URL: Repository, https://github.com/MannLabs/alphabase
Project-URL: Documentation, https://alphabase.readthedocs.io/en/latest/
Project-URL: Issues, https://github.com/MannLabs/alphabase/issues
Project-URL: Mann Labs Homepage, https://www.biochem.mpg.de/mann
Keywords: mass spectrometry,proteomics,bioinformatics,AlphaPept,AlphaPept ecosystem,AlphaX ecosystem
Classifier: Development Status :: 4 - Beta
Classifier: Intended Audience :: Science/Research
Classifier: License :: OSI Approved :: Apache Software License
Classifier: Operating System :: OS Independent
Classifier: Programming Language :: Python :: 3
Classifier: Topic :: Scientific/Engineering :: Bio-Informatics
Requires-Python: >=3.8
License-File: LICENSE.txt
Requires-Dist: numba
Requires-Dist: numpy
Requires-Dist: pandas
Requires-Dist: h5py
Requires-Dist: contextlib2
Requires-Dist: xxhash
Requires-Dist: biopython
Requires-Dist: tqdm
Requires-Dist: regex
Requires-Dist: pyarrow
Requires-Dist: pyahocorasick
Requires-Dist: pyteomics
Requires-Dist: pyyaml
Requires-Dist: lxml
Requires-Dist: rdkit
Provides-Extra: stable
Requires-Dist: numba==0.60.0; extra == "stable"
Requires-Dist: numpy<2.0; extra == "stable"
Requires-Dist: pandas==2.2.3; extra == "stable"
Requires-Dist: h5py==3.12.1; extra == "stable"
Requires-Dist: contextlib2==21.6.0; extra == "stable"
Requires-Dist: xxhash==3.5.0; extra == "stable"
Requires-Dist: biopython==1.84; extra == "stable"
Requires-Dist: tqdm==4.67.0; extra == "stable"
Requires-Dist: regex==2024.11.6; extra == "stable"
Requires-Dist: pyarrow==19.0.1; extra == "stable"
Requires-Dist: pyahocorasick==2.1.0; extra == "stable"
Requires-Dist: pyteomics==4.7.5; extra == "stable"
Requires-Dist: pyyaml==6.0.2; extra == "stable"
Requires-Dist: lxml==5.3.0; extra == "stable"
Requires-Dist: rdkit==2024.3.3; extra == "stable"
Provides-Extra: dask
Requires-Dist: dask; extra == "dask"
Requires-Dist: dask_expr; extra == "dask"
Provides-Extra: dask-stable
Requires-Dist: dask==2024.8.0; extra == "dask-stable"
Requires-Dist: dask_expr==1.1.10; extra == "dask-stable"
Provides-Extra: hdf
Requires-Dist: tables; extra == "hdf"
Provides-Extra: tests
Requires-Dist: pre-commit==3.7.0; extra == "tests"
Requires-Dist: nbmake==1.5.3; extra == "tests"
Requires-Dist: matplotlib; extra == "tests"
Requires-Dist: pytest; extra == "tests"
Requires-Dist: anndata==0.10.8; extra == "tests"
Requires-Dist: mudata==0.2.4; extra == "tests"
Provides-Extra: development
Requires-Dist: jupyter; extra == "development"
Requires-Dist: bump-my-version; extra == "development"
Requires-Dist: ipykernel; extra == "development"
Requires-Dist: pre-commit==3.7.0; extra == "development"
Requires-Dist: nbmake==1.5.3; extra == "development"
Requires-Dist: matplotlib; extra == "development"
Requires-Dist: pytest; extra == "development"
Requires-Dist: anndata==0.10.8; extra == "development"
Requires-Dist: mudata==0.2.4; extra == "development"
Requires-Dist: autodocsumm; extra == "development"
Requires-Dist: myst_parser; extra == "development"
Requires-Dist: sphinx; extra == "development"
Requires-Dist: nbsphinx; extra == "development"
Requires-Dist: jinja2; extra == "development"
Requires-Dist: contextfilter; extra == "development"
Requires-Dist: furo; extra == "development"
Requires-Dist: anndata==0.10.8; extra == "development"
Requires-Dist: mudata==0.2.4; extra == "development"
Dynamic: license-file
